pylems_py2xml/__init__.py
pylems_py2xml/main.py
pylems_py2xml/models.py
pylems_py2xml/utils.py
pylems_py2xml/data/hindmarshrose.xml
pylems_py2xml/data/oscillator.xml
pylems_py2xml-1.0.10.dist-info/LICENSE
pylems_py2xml-1.0.10.dist-info/METADATA
pylems_py2xml-1.0.10.dist-info/WHEEL
pylems_py2xml-1.0.10.dist-info/top_level.txt
pylems_py2xml-1.0.10.dist-info/RECORD
