Metadata-Version: 2.1
Name: pylems-py2xml
Version: 1.0.10
Summary: Python code & dictionary traversal to XML
Home-page: https://github.com/dissagaliyeva/pylems-ext
Author: Dinara Issagaliyeva
Author-email: dinarissaa@gmail.com
License: MIT
Keywords: pylems,xml
Platform: UNKNOWN
Classifier: Development Status :: 5 - Production/Stable
Classifier: Intended Audience :: Science/Research
Classifier: Operating System :: Microsoft :: Windows :: Windows 11
Classifier: License :: OSI Approved :: MIT License
Classifier: Programming Language :: Python :: 3
License-File: LICENSE
Requires-Dist: pylems
